example/__init__.py
example/example_code.py
tests/__init__.py
tests/tests.py
theos-0.0.1.dist-info/LICENSE.txt
theos-0.0.1.dist-info/METADATA
theos-0.0.1.dist-info/WHEEL
theos-0.0.1.dist-info/top_level.txt
theos-0.0.1.dist-info/RECORD
