Metadata-Version: 2.1
Name: theos
Version: 0.0.1
Summary: A cross-platform suite of tools for building and deploying software for iOS and other platforms.
Home-page: https://github.com/theos/theos
Author: theos
Author-email: web@theos.dev
License: GPL v3
Project-URL: Funding, https://donate.pypi.org
Project-URL: Documentation, https://github.com/theos/theos
Keywords: theos
Platform: UNKNOWN
Classifier: Development Status :: 3 - Alpha
Classifier: License :: OSI Approved :: MIT License
Classifier: Programming Language :: Python :: 3.6
Classifier: Programming Language :: Python :: 3.7
Requires-Python: >=3.6
